wagtail_model_tools
